neon_goby/__init__.py
neon_goby/clean.py
neon_goby/constants.py
neon_goby/matchers.py
neon_goby/split.py
tests/__init__.py
tests/test_neon_goby.py
neon_goby-0.0.1.dist-info/METADATA
neon_goby-0.0.1.dist-info/WHEEL
neon_goby-0.0.1.dist-info/top_level.txt
neon_goby-0.0.1.dist-info/RECORD
