Metadata-Version: 2.1
Name: neon-goby
Version: 0.0.1
Summary: A simple package to clean email bodies
Home-page: https://github.com/pypa/sampleproject
Author: HiiYL
Author-email: hii@saleswhale.com
License: UNKNOWN
Platform: UNKNOWN
Classifier: Programming Language :: Python :: 3
Classifier: Operating System :: OS Independent
Requires-Python: >=3.6
Requires-Dist: contractions (==0.0.23)
Requires-Dist: email-reply-parser (==0.5.9)
Requires-Dist: syntok (==1.2.1)
Requires-Dist: beautifulsoup4 (==4.7.1)
